llm_factory/__init__.py
llm_factory/factory_llm.py
llm_factory/providers/__init__.py
llm_factory/providers/anthropic_provider.py
llm_factory/providers/deepseek_provider.py
llm_factory/providers/fireworks_provider.py
llm_factory/providers/huggingface_provider.py
llm_factory/providers/ollama_provider.py
llm_factory/providers/openai_provider.py
llm_factory/providers/vllm_provider.py
ecq_llmfactory-0.1.20.dist-info/METADATA
ecq_llmfactory-0.1.20.dist-info/WHEEL
ecq_llmfactory-0.1.20.dist-info/top_level.txt
ecq_llmfactory-0.1.20.dist-info/RECORD
