Metadata-Version: 2.1
Name: ecq_llmfactory
Version: 0.1.20
Summary: LLMFactory is a modular framework built on LangChain...
Home-page: https://kappa.e-cq.net/linh.vo/llmfactory
Author: Linh Vo
Author-email: linh.vo@e-cq.net
Classifier: Programming Language :: Python :: 3
Classifier: License :: OSI Approved :: MIT License
Classifier: Operating System :: OS Independent
Requires-Python: >=3.9
Requires-Dist: langchain==0.3.24
Requires-Dist: python-dotenv
Requires-Dist: setuptools==72.1.0
Requires-Dist: langchain-community==0.3.22
Provides-Extra: all
Requires-Dist: langchain-anthropic==0.3.3; extra == "all"
Requires-Dist: langchain-fireworks==0.2.6; extra == "all"
Requires-Dist: langchain-huggingface==0.1.2; extra == "all"
Requires-Dist: langchain-ollama==0.2.2; extra == "all"
Requires-Dist: langchain-openai==0.3.1; extra == "all"
Requires-Dist: transformers==4.44.2; extra == "all"
Provides-Extra: anthropic
Requires-Dist: langchain-anthropic==0.3.3; extra == "anthropic"
Provides-Extra: deepseek
Requires-Dist: langchain-openai==0.3.1; extra == "deepseek"
Provides-Extra: fireworks
Requires-Dist: langchain-fireworks==0.2.6; extra == "fireworks"
Provides-Extra: huggingface
Requires-Dist: langchain-huggingface==0.1.2; extra == "huggingface"
Requires-Dist: transformers==4.44.2; extra == "huggingface"
Provides-Extra: ollama
Requires-Dist: langchain-ollama==0.2.2; extra == "ollama"
Provides-Extra: openai
Requires-Dist: langchain-openai==0.3.1; extra == "openai"
Provides-Extra: vllm
Requires-Dist: langchain-openai==0.3.1; extra == "vllm"
